LICENSE.txt
README.md
setup.py
WAVES_Utilities.egg-info/PKG-INFO
WAVES_Utilities.egg-info/SOURCES.txt
WAVES_Utilities.egg-info/dependency_links.txt
WAVES_Utilities.egg-info/requires.txt
WAVES_Utilities.egg-info/top_level.txt
waves_utilities/__init__.py
waves_utilities/api.py
waves_utilities/constants.py
waves_utilities/csv_manager.py
waves_utilities/plot.py
waves_utilities/types.py
waves_utilities/util.py
waves_utilities.egg-info/PKG-INFO
waves_utilities.egg-info/SOURCES.txt
waves_utilities.egg-info/dependency_links.txt
waves_utilities.egg-info/requires.txt
waves_utilities.egg-info/top_level.txt