Metadata-Version: 2.1
Name: waves-utilities
Version: 1.0.0
Summary: SURF WAVES physiological waveform dataset utilities
Home-page: https://bitbucket.org/surfstanfordmedicine/waves-utilities
Author: Daniel Miller
Author-email: danielroymiller@gmail.com
License: MIT
License-File: LICENSE.txt
